guardpost/__about__.py
guardpost/__init__.py
guardpost/abc.py
guardpost/authentication.py
guardpost/authorization.py
guardpost/common.py
guardpost/errors.py
guardpost/protection.py
guardpost/py.typed
guardpost/utils.py
guardpost/jwks/__init__.py
guardpost/jwks/caching.py
guardpost/jwks/openid.py
guardpost/jwks/urls.py
guardpost/jwts/__init__.py
guardpost-1.0.4.dist-info/METADATA
guardpost-1.0.4.dist-info/WHEEL
guardpost-1.0.4.dist-info/licenses/LICENSE
guardpost-1.0.4.dist-info/RECORD
