Metadata-Version: 2.4
Name: guardpost
Version: 1.0.4
Summary: Framework to handle authentication and authorization.
Project-URL: Homepage, https://github.com/Neoteroi/GuardPost
Project-URL: Bug Tracker, https://github.com/Neoteroi/GuardPost/issues
Author-email: Roberto Prevato <roberto.prevato@gmail.com>
License-Expression: MIT
License-File: LICENSE
Keywords: authentication,authorization,claims,identity,strategy
Classifier: Development Status :: 5 - Production/Stable
Classifier: License :: OSI Approved :: MIT License
Classifier: Operating System :: OS Independent
Classifier: Programming Language :: Python :: 3
Classifier: Programming Language :: Python :: 3.10
Classifier: Programming Language :: Python :: 3.11
Classifier: Programming Language :: Python :: 3.12
Classifier: Programming Language :: Python :: 3.13
Classifier: Programming Language :: Python :: 3.14
Requires-Python: >=3.10
Requires-Dist: rodi>=2.0.0
Requires-Dist: typing-extensions; python_version < '3.8'
Provides-Extra: jwt
Requires-Dist: cryptography; extra == 'jwt'
Requires-Dist: essentials<2.0,>=1.1.8; extra == 'jwt'
Requires-Dist: pyjwt; extra == 'jwt'
